{"noiseKey":{"private":{"type":"Buffer","data":"GNtGu/R0BE3qzzTiKCYDNiZiewALEBJ59XpV6z2dyVs="},"public":{"type":"Buffer","data":"BbJjm5oqrIjDy1+MbJzadQ6FAJoSSQOx1I2DsL+jQUk="}},"pairingEphemeralKeyPair":{"private":{"type":"Buffer","data":"MHJbQJUSROQD2T999Dsv1kr87/oi3cPRGH2tYTOgOl8="},"public":{"type":"Buffer","data":"9upfkcLnh0SNBFyi+Mq3A5YVpV9Edvl4GHTkWhiBnFw="}},"signedIdentityKey":{"private":{"type":"Buffer","data":"WJD+SjgeP1amKC+mFmmEStla/KG4cZZhmXGzqXPRmGQ="},"public":{"type":"Buffer","data":"5sMLDn8bdp8ubcV3nbMmlStohsoGkiaxR2RoI8Z56B0="}},"signedPreKey":{"keyPair":{"private":{"type":"Buffer","data":"ENBC1x6qbx8xRF1XCRR6uKJY93fwrT0pdB8BX8bcVno="},"public":{"type":"Buffer","data":"B2E+l+NaeTJNSemEmNwJo9D5BQsbKyKKUlcfrKtZmB4="}},"signature":{"type":"Buffer","data":"wAnO6OtEghhSu0JXWEkOFaMXs7EnVzeRo+Nr+VhpKwf8iTPprWznNgFV97Zr45URDNNwuY6MEdiRqsEXMQLoBQ=="},"keyId":1},"registrationId":223,"advSecretKey":"J8TmIEZJjUYZXi6Qj/gAlyVjJicVXH7mYVr8DpK/EYU=","processedHistoryMessages":[{"key":{"remoteJid":"559180625187@s.whatsapp.net","fromMe":false,"id":"ACDBF7F3F351C9D5970CD2087AB3F194","participant":"","addressingMode":"pn"},"messageTimestamp":1768420139},{"key":{"remoteJid":"559180625187@s.whatsapp.net","fromMe":false,"id":"AC88FDC6AC8C136C12F83AF4E84A97E4","participant":"","addressingMode":"pn"},"messageTimestamp":1768420139},{"key":{"remoteJid":"559180625187@s.whatsapp.net","fromMe":false,"id":"ACBF6A5708F6924D1A9D40659F3FDFD0","participant":"","addressingMode":"pn"},"messageTimestamp":1768420139},{"key":{"remoteJid":"559180625187@s.whatsapp.net","fromMe":false,"id":"ACA1EBB16A90E508A977FA02F7E57679","participant":"","addressingMode":"pn"},"messageTimestamp":1768420139},{"key":{"remoteJid":"559180625187@s.whatsapp.net","fromMe":false,"id":"AC500F6FC7385FF3192F891DAA86D726","participant":"","addressingMode":"pn"},"messageTimestamp":1768420157},{"key":{"remoteJid":"559180625187@s.whatsapp.net","fromMe":false,"id":"AC463E1D5E5946C4A2A3349B3622BDE1","participant":"","addressingMode":"pn"},"messageTimestamp":1768420165},{"key":{"remoteJid":"559180625187@s.whatsapp.net","fromMe":false,"id":"AC4B24BD175971A5BED8468F3AB54A38","participant":"","addressingMode":"pn"},"messageTimestamp":1768420172},{"key":{"remoteJid":"559180625187@s.whatsapp.net","fromMe":false,"id":"AC249AECD7BFA93ADD7C223D8723C4BE","participant":"","addressingMode":"pn"},"messageTimestamp":1768420179},{"key":{"remoteJid":"559180625187@s.whatsapp.net","fromMe":false,"id":"AC8C6FFE1053E692B46E17D14A77BB40","participant":"","addressingMode":"pn"},"messageTimestamp":1768420186},{"key":{"remoteJid":"559180625187@s.whatsapp.net","fromMe":false,"id":"AC561B11C73EF19EA0D1B4BCC93E46F8","participant":"","addressingMode":"pn"},"messageTimestamp":1768420194},{"key":{"remoteJid":"559180625187@s.whatsapp.net","fromMe":false,"id":"AC8F32DDDC1A736F2B9694305B8466C3","participant":"","addressingMode":"pn"},"messageTimestamp":1768420201},{"key":{"remoteJid":"559180625187@s.whatsapp.net","fromMe":false,"id":"AC9EE5131FC70E60395611840303CE06","participant":"","addressingMode":"pn"},"messageTimestamp":1768420208},{"key":{"remoteJid":"559180625187@s.whatsapp.net","fromMe":false,"id":"ACCA8DC3509CF3890FC8115F4BAFC288","participant":"","addressingMode":"pn"},"messageTimestamp":1768420214},{"key":{"remoteJid":"559180625187@s.whatsapp.net","fromMe":false,"id":"AC381DCB55AC8E0FF5CB1DF91EBCC6AC","participant":"","addressingMode":"pn"},"messageTimestamp":1768420220},{"key":{"remoteJid":"559180625187@s.whatsapp.net","fromMe":false,"id":"ACBD00453607C1AEF0F8ECB1A020147F","participant":"","addressingMode":"pn"},"messageTimestamp":1768420227},{"key":{"remoteJid":"559180625187@s.whatsapp.net","fromMe":false,"id":"ACFCADF23DFBB52F98D7308C49FB9E77","participant":"","addressingMode":"pn"},"messageTimestamp":1768420234},{"key":{"remoteJid":"559180625187@s.whatsapp.net","fromMe":false,"id":"ACF6EADEAD26C0A736C016825FE38563","participant":"","addressingMode":"pn"},"messageTimestamp":1768420241},{"key":{"remoteJid":"559180625187@s.whatsapp.net","fromMe":false,"id":"ACB64229BAA873B19B386D1979B697AB","participant":"","addressingMode":"pn"},"messageTimestamp":1768420247},{"key":{"remoteJid":"559180625187@s.whatsapp.net","fromMe":false,"id":"ACDC4A65F75DA1BAB13385CD0332ADED","participant":"","addressingMode":"pn"},"messageTimestamp":1768420254},{"key":{"remoteJid":"559180625187@s.whatsapp.net","fromMe":false,"id":"AC5E7D151F230D4F4ECF6B2AEAF48B6B","participant":"","addressingMode":"pn"},"messageTimestamp":1768420260},{"key":{"remoteJid":"559180625187@s.whatsapp.net","fromMe":false,"id":"ACE78A434E425435178180341F5CBC5E","participant":"","addressingMode":"pn"},"messageTimestamp":1768420267},{"key":{"remoteJid":"559180625187@s.whatsapp.net","fromMe":false,"id":"ACA7C8E0FED63446EFCBB1AB7E397E22","participant":"","addressingMode":"pn"},"messageTimestamp":1768420272},{"key":{"remoteJid":"559180625187@s.whatsapp.net","fromMe":false,"id":"ACCA8C1A2672461CAE8A9DA9EB8E5C91","participant":"","addressingMode":"pn"},"messageTimestamp":1768420279},{"key":{"remoteJid":"559180625187@s.whatsapp.net","fromMe":false,"id":"AC950927C1111287344DB948EBEF4522","participant":"","addressingMode":"pn"},"messageTimestamp":1768420285},{"key":{"remoteJid":"559180625187@s.whatsapp.net","fromMe":false,"id":"ACB3B30709CF3B450BFFAADCDF61CF55","participant":"","addressingMode":"pn"},"messageTimestamp":1768420292},{"key":{"remoteJid":"559180625187@s.whatsapp.net","fromMe":false,"id":"AC7E62F3BAF8518E1A2543FF161415EB","participant":"","addressingMode":"pn"},"messageTimestamp":1768420300},{"key":{"remoteJid":"559180625187@s.whatsapp.net","fromMe":false,"id":"ACD68155465D3340455EE19133F3468F","participant":"","addressingMode":"pn"},"messageTimestamp":1768420306},{"key":{"remoteJid":"559180625187@s.whatsapp.net","fromMe":false,"id":"AC9E3C26FD429F588598EDD7CC664EC6","participant":"","addressingMode":"pn"},"messageTimestamp":1768420313},{"key":{"remoteJid":"559180625187@s.whatsapp.net","fromMe":false,"id":"AC04E6F339453532750BCF17C1D36E7F","participant":"","addressingMode":"pn"},"messageTimestamp":1768420321},{"key":{"remoteJid":"559180625187@s.whatsapp.net","fromMe":false,"id":"AC35CF80F7F351444B38DD927C8C22F5","participant":"","addressingMode":"pn"},"messageTimestamp":1768420328},{"key":{"remoteJid":"559180625187@s.whatsapp.net","fromMe":false,"id":"AC24BB0B902911FBFEC31EF68F4F0F63","participant":"","addressingMode":"pn"},"messageTimestamp":1768420332},{"key":{"remoteJid":"559180625187@s.whatsapp.net","fromMe":false,"id":"AC5988B0D4FAF9B533C300315CE2573B","participant":"","addressingMode":"pn"},"messageTimestamp":1768420341},{"key":{"remoteJid":"559180625187@s.whatsapp.net","fromMe":false,"id":"ACB423B341AD397E1FBED28FCEFB8C43","participant":"","addressingMode":"pn"},"messageTimestamp":1768420350},{"key":{"remoteJid":"559180625187@s.whatsapp.net","fromMe":false,"id":"AC130FF8BFCA2E9B254CCDC1ED3A40B8","participant":"","addressingMode":"pn"},"messageTimestamp":1768420358},{"key":{"remoteJid":"559180625187@s.whatsapp.net","fromMe":false,"id":"AC2BD1EE15E46B6CF4D70D40FC22E2A0","participant":"","addressingMode":"pn"},"messageTimestamp":1768420366},{"key":{"remoteJid":"559180625187@s.whatsapp.net","fromMe":false,"id":"AC7D4BA7B94F37615EA4DB722E1FDAAA","participant":"","addressingMode":"pn"},"messageTimestamp":1768420375},{"key":{"remoteJid":"559180625187@s.whatsapp.net","fromMe":false,"id":"AC91B4D9B7FB362C07D38682FA53B1B9","participant":"","addressingMode":"pn"},"messageTimestamp":1768420382}],"nextPreKeyId":814,"firstUnuploadedPreKeyId":814,"accountSyncCounter":1,"accountSettings":{"unarchiveChats":false},"registered":false,"account":{"details":"CKann9oHEJ3mn8sGGAEgACgA","accountSignatureKey":"B7Ds7oSVvJPrewVpXRrQ4VD+6CLDT0cW0hqA1D8CPXQ=","accountSignature":"CaSpkMQ1QvUVrP3J0RE3B0j5xNqmTG9l3DP2jUS0duhf6UZl/X441n37cg5kC5gnw0exCOjLqTZ8+IMpUc0zBQ==","deviceSignature":"A+B4duOw6uV7w+Xs/F44aXLgk4nK51iX+GZHOsGkiH3Vi1zwUMLPjcksoRjWPSbApjl803/UIO4BDgXIqG47BA=="},"me":{"id":"559180625187:85@s.whatsapp.net","lid":"69389575557357:85@lid","name":"Cae"},"signalIdentities":[{"identifier":{"name":"69389575557357:85@lid","deviceId":0},"identifierKey":{"type":"Buffer","data":"BQew7O6ElbyT63sFaV0a0OFQ/ugiw09HFtIagNQ/Aj10"}}],"platform":"android","routingInfo":{"type":"Buffer","data":"CAgIEggF"},"lastAccountSyncTimestamp":1768420134,"lastPropHash":"1K4hH4","myAppStateKeyId":"AAAAAGm4"}